pdfman/__init__.py
pdfman/cli.py
pdfman/main.py
pdfman-1.0.0.dist-info/METADATA
pdfman-1.0.0.dist-info/WHEEL
pdfman-1.0.0.dist-info/entry_points.txt
pdfman-1.0.0.dist-info/top_level.txt
pdfman-1.0.0.dist-info/RECORD
