Metadata-Version: 2.1
Name: pdfman
Version: 1.0.0
Summary: A python package for editing pdf
Home-page: https://github.com/jakbin/pdfman
Author: Jak Bin
Project-URL: Bug Tracker, https://github.com/jakbin/pdfman/issues
Keywords: pdf,python-pdf,splitpdf,pypdf,pdfman
Classifier: Programming Language :: Python :: 3
Classifier: License :: OSI Approved :: MIT License
Classifier: Operating System :: OS Independent
Requires-Python: >=3.6
Requires-Dist: PyPDF2
